LICENSE
MANIFEST.in
README.md
requirements.txt
setup.cfg
setup.py
django_model_search.egg-info/PKG-INFO
django_model_search.egg-info/SOURCES.txt
django_model_search.egg-info/dependency_links.txt
django_model_search.egg-info/requires.txt
django_model_search.egg-info/top_level.txt
model_search/__init__.py
model_search/admin.py
model_search/lib.py
model_search/models.py
model_search/tests.py
model_search/translation.py
model_search/locale/en/LC_MESSAGES/django.mo
model_search/locale/en/LC_MESSAGES/django.po
model_search/locale/ru/LC_MESSAGES/django.mo
model_search/locale/ru/LC_MESSAGES/django.po
model_search/locale/uk/LC_MESSAGES/django.mo
model_search/locale/uk/LC_MESSAGES/django.po
model_search/migrations/0001_initial.py
model_search/migrations/__init__.py