Metadata-Version: 2.1
Name: django-model-search
Version: 2.2.1
Summary: Django search package
Home-page: https://github.com/pmaigutyak/mp-search
Author: Paul Maigutyak
Author-email: pmaigutyak@gmail.com
License: MIT
Download-URL: https://github.com/pmaigutyak/mp-search/archive/2.2.1.tar.gz
Platform: UNKNOWN
License-File: LICENSE
